README.rst
setup.cfg
setup.py
hrf_estimation/__init__.py
hrf_estimation/data.py
hrf_estimation/hrf.py
hrf_estimation/rank_one_.py
hrf_estimation/savitzky_golay.py
hrf_estimation/utils.py
hrf_estimation.egg-info/PKG-INFO
hrf_estimation.egg-info/SOURCES.txt
hrf_estimation.egg-info/dependency_links.txt
hrf_estimation.egg-info/top_level.txt