Metadata-Version: 1.1
Name: hrf-estimation
Version: 1.0
Summary: A module for estimating Hemodynamical Response Function from functional MRI data
Home-page: https://pypi.python.org/pypi/hrf_estimation
Author: Fabian Pedregosa
Author-email: fabian@fseoane.net
License: Simplified BSD
Platform: UNKNOWN
Classifier: Development Status :: 5 - Production/Stable
Classifier: Intended Audience :: Science/Research
Classifier: Intended Audience :: Developers
Classifier: License :: OSI Approved
Classifier: Programming Language :: Python
Classifier: Programming Language :: Python :: 3
Classifier: Topic :: Software Development
Classifier: Operating System :: POSIX
Classifier: Operating System :: Unix
